toggl_to_redmine/CLI.py
toggl_to_redmine/__init__.py
toggl_to_redmine/config_manager.py
toggl_to_redmine/options.py
toggl_to_redmine/app/__init__.py
toggl_to_redmine/app/config.py
toggl_to_redmine/app/exceptions.py
toggl_to_redmine/app/time_entry.py
toggl_to_redmine/app/toggl_to_redmine.py
toggl_to_redmine/integrations/__init__.py
toggl_to_redmine/integrations/redmine_integrator.py
toggl_to_redmine/integrations/toggl_integrator.py
toggl_to_redmine/platforms/CLI_config_manager.py
toggl_to_redmine/platforms/CLI_platform.py
toggl_to_redmine/platforms/__init__.py
toggl_to_redmine/platforms/base_platform.py
toggl_to_redmine-1.4.0.dist-info/METADATA
toggl_to_redmine-1.4.0.dist-info/WHEEL
toggl_to_redmine-1.4.0.dist-info/entry_points.txt
toggl_to_redmine-1.4.0.dist-info/top_level.txt
toggl_to_redmine-1.4.0.dist-info/RECORD
