Metadata-Version: 2.1
Name: toggl-to-redmine
Version: 1.4.0
Summary: Easily import time entries from Toggl to Redmine
Home-page: https://github.com/eduardocanellas/toggl-to-redmine
Author: Eduardo Canellas
Author-email: eduardocanellas@id.uff.br
License: UNKNOWN
Platform: UNKNOWN
Classifier: Programming Language :: Python :: 3
Classifier: License :: OSI Approved :: MIT License
Classifier: Operating System :: OS Independent
Requires-Python: >=3.6
